{"inkVersion":20,"root":[["^The Alibi ",{"#":"format title"},"\n","^A man is dead, and I know who did it. But I have no proof. ",{"#":"enable brown"},"\n",["ev",{"^->":"0.6.$r1"},{"temp=":"$r"},"str",{"->":".^.s"},[{"#n":"$r1"}],"/str","str","^.","/str","/ev",{"*":"0.c-0","flg":6},{"s":["^Doctor Bigeyes Brown",{"->":"$r","var":true},null]}],{"c-0":["ev",{"^->":"0.c-0.$r2"},"/ev",{"temp=":"$r"},{"->":"0.6.s"},[{"#n":"$r2"}],"<>","^ ",{"#":"label brown Dr. BROWN"},{"#":"art brown dogs/brown-greyscale"},"\n",{"->":"0.g-0"},{"#f":5}],"g-0":["^was shot at 4 PM. The killing hour. They say he was a good boy - who isn't, these days?","\n",["ev",{"^->":"0.g-0.2.$r1"},{"temp=":"$r"},"str",{"->":".^.s"},[{"#n":"$r1"}],"/str","/ev",{"*":".^.^.c-1","flg":2},{"s":["^Somebody thought otherwise, and they had a gun. ",{"->":"$r","var":true},null]}],{"c-1":["ev",{"^->":"0.g-0.c-1.$r2"},"/ev",{"temp=":"$r"},{"->":".^.^.2.s"},[{"#n":"$r2"}],{"#":"enable red"},{"#":"enable red.suspect"},"\n",{"->":"0.g-1"},{"#f":5}],"#f":5}],"g-1":["^It had to be the secretary, Russet. Brown stole and buried his bone. Intolerable to a certain type.","\n","^It was easy enough to find the murder weapon - an old service firearm, unregistered, the kind your grandfather left in the attic after the War. Russet has that kind of grandfather.","\n",["ev",{"^->":"0.g-1.4.$r1"},{"temp=":"$r"},"str",{"->":".^.s"},[{"#n":"$r1"}],"/str","/ev",{"*":".^.^.c-2","flg":2},{"s":["^He also has an alibi. ",{"->":"$r","var":true},null]}],{"c-2":["ev",{"^->":"0.g-1.c-2.$r2"},"/ev",{"temp=":"$r"},{"->":".^.^.4.s"},[{"#n":"$r2"}],"\n",{"->":"0.g-2"},{"#f":5}],"#f":5}],"g-2":["^From 3 to 5, Russet was playing in the park... with the most trustworthy woman in the world. He claims they spent every moment in each other's company - fetch, chasey, the whole nine yards. And his companion backs him up. ",{"#":"enable red.alibi"},"\n",["ev",{"^->":"0.g-2.3.$r1"},{"temp=":"$r"},"str",{"->":".^.s"},[{"#n":"$r1"}],"/str","/ev",{"*":".^.^.c-3","flg":2},{"s":["^Madame Goldsmith is a good boy.",{"->":"$r","var":true},null]}],["ev",{"^->":"0.g-2.4.$r1"},{"temp=":"$r"},"str",{"->":".^.s"},[{"#n":"$r1"}],"/str","/ev",{"*":".^.^.c-4","flg":2},{"s":["^Madame Goldsmith is a very good boy.",{"->":"$r","var":true},null]}],{"c-3":["ev",{"^->":"0.g-2.c-3.$r2"},"/ev",{"temp=":"$r"},{"->":".^.^.3.s"},[{"#n":"$r2"}],"\n",{"->":"0.g-3"},{"#f":5}],"c-4":["ev",{"^->":"0.g-2.c-4.$r2"},"/ev",{"temp=":"$r"},{"->":".^.^.4.s"},[{"#n":"$r2"}],"\n",{"->":"0.g-3"},{"#f":5}],"#f":5}],"g-3":["<>","^ She'd never lie, not with lives on the line. ",{"#":"enable gold"},{"#":"enable gold.witness"},"\n",{"->":"who_first"},["done",{"#f":5,"#n":"g-4"}],{"#f":5}]}],"done",{"who_first":[["^My only chance now is to talk to people and ask them questions. ",["ev","visit",1,"MIN","/ev","ev","du",0,"==","/ev",{"->":".^.s0","c":true},"ev","du",1,"==","/ev",{"->":".^.s1","c":true},"nop",{"s0":["pop","^But who?",{"->":".^.^.17"},null],"s1":["pop","^Who else?",{"->":".^.^.17"},null],"#f":5}],"^ ",{"#":"plot-choices"},"\n","ev","str","^click.red","/str","/ev",{"*":".^.c-0","flg":4},"ev","str","^click.brown","/str","/ev",{"*":".^.c-1","flg":4},"ev","str","^click.gold","/str","/ev",{"*":".^.c-2","flg":4},{"c-0":["^ ",{"->t->":"interview_red"},{"->":".^.^.^"},"\n",{"#f":5}],"c-1":["^ ",{"->t->":"interview_brown"},{"->":".^.^.^"},"\n",{"#f":5}],"c-2":["^ ",{"->t->":"interview_gold"},{"->":"who_next"},"\n",{"#f":5}]}],{"#f":1}],"who_next":[["^I still have questions. ",{"#":"plot-choices"},"\n","ev","str","^click.red","/str","/ev",{"*":".^.c-0","flg":4},"ev","str","^click.brown","/str","/ev",{"*":".^.c-1","flg":4},"ev","str","^click.gold","/str","/ev",{"*":".^.c-2","flg":4},{"c-0":["^ ",{"->":"accuse_red"},"\n",{"#f":5}],"c-1":["^ ",{"->t->":"interview_brown"},{"->":".^.^.^"},"\n",{"#f":5}],"c-2":["^ ",{"->t->":"interview_gold"},{"->":".^.^.^"},"\n",{"#f":5}]}],{"#f":1}],"interview_brown":["^He's dead, Jim.","\n","ev","void","/ev","->->",{"#f":1}],"interview_red":[[{"#":"format begin-interview"},"^Subject: Rupert RUSSET ",{"#":"format title"},"\n","^\"I didn't do it.\"","\n",["ev",{"^->":"interview_red.0.6.$r1"},{"temp=":"$r"},"str",{"->":".^.s"},[{"#n":"$r1"}],"/str","/ev",{"*":".^.^.c-0","flg":2},{"s":["^\"Ok.\"",{"->":"$r","var":true},null]}],{"c-0":["ev",{"^->":"interview_red.0.c-0.$r2"},"/ev",{"temp=":"$r"},{"->":".^.^.6.s"},[{"#n":"$r2"}],"\n",{"#":"format end-interview"},{"->":".^.^.g-0"},{"#f":5}],"g-0":["ev","void","/ev","->->",{"#f":5}]}],{"#f":1}],"interview_gold":[[{"#":"format begin-interview"},"^Subject: Gloria GOLDSMITH ",{"#":"format title"},"\n","^\"Actually, he did it.\" ",{"#":"label red.alibi No alibi"},"\n",["ev",{"^->":"interview_gold.0.7.$r1"},{"temp=":"$r"},"str",{"->":".^.s"},[{"#n":"$r1"}],"/str","/ev",{"*":".^.^.c-0","flg":2},{"s":["^\"Oh.\"",{"->":"$r","var":true},null]}],{"c-0":["ev",{"^->":"interview_gold.0.c-0.$r2"},"/ev",{"temp=":"$r"},{"->":".^.^.7.s"},[{"#n":"$r2"}],"\n",{"#":"format end-interview"},{"->":".^.^.g-0"},{"#f":5}],"g-0":["ev","void","/ev","->->",{"#f":5}]}],{"#f":1}],"accuse_red":[{"#":"format begin-interview"},"^Subject: Rupert RUSSET ",{"#":"format title"},"\n","^\"Actually, I did it.\"","\n",{"#":"format end-interview"},"^~fin","\n","end",{"#f":1}],"#f":1}],"listDefs":{}}